barc4sr/__init__.py
barc4sr/aux_energy.py
barc4sr/aux_potpourri.py
barc4sr/aux_processing.py
barc4sr/aux_syned.py
barc4sr/aux_time.py
barc4sr/aux_utils.py
barc4sr/aux_wavefronts.py
barc4sr/sr_arb_mag_field.py
barc4sr/sr_bending_magnet.py
barc4sr/sr_classes.py
barc4sr/sr_undulator.py
barc4sr/sr_wiggler.py
examples/__init__.py
barc4sr-2024.12.4.dist-info/LICENSE
barc4sr-2024.12.4.dist-info/METADATA
barc4sr-2024.12.4.dist-info/WHEEL
barc4sr-2024.12.4.dist-info/top_level.txt
barc4sr-2024.12.4.dist-info/RECORD
