Metadata-Version: 2.1
Name: barc4sr
Version: 2024.12.4
Summary: A Python package for Synchrotron Radiation calculations
Home-page: https://github.com/barc4/barc4sr
Author: Rafael Celestre
Author-email: rafael.celestre@synchrotron-soleil.fr
License: GPL-3.0
Classifier: Development Status :: 3 - Alpha
Classifier: License :: OSI Approved :: GNU General Public License v3 (GPLv3)
Classifier: Programming Language :: Python :: 3
Classifier: Programming Language :: Python :: 3.6
Classifier: Programming Language :: Python :: 3.7
Classifier: Programming Language :: Python :: 3.8
Classifier: Programming Language :: Python :: 3.9
License-File: LICENSE
Requires-Dist: numpy >=1.20
Requires-Dist: numba >=0.53.1
Requires-Dist: scipy >=1.5.0
Requires-Dist: joblib >=0.14.0
Requires-Dist: h5py >=3.0.0
Requires-Dist: matplotlib >=3.3.0
Requires-Dist: Pillow >=7.0.0
Requires-Dist: imageio >=2.9.0
Requires-Dist: scikit-image >=0.17.2
